README.md
setup.cfg
setup.py
dslink/Crypto.py
dslink/DSLink.py
dslink/FileStorage.py
dslink/Handshake.py
dslink/Node.py
dslink/Permission.py
dslink/Profile.py
dslink/Request.py
dslink/Requester.py
dslink/Responder.py
dslink/Response.py
dslink/Serializers.py
dslink/Storage.py
dslink/Util.py
dslink/Value.py
dslink/WebSocket.py
dslink/__init__.py
dslink/six.py
dslink.egg-info/PKG-INFO
dslink.egg-info/SOURCES.txt
dslink.egg-info/dependency_links.txt
dslink.egg-info/requires.txt
dslink.egg-info/top_level.txt
dslink/rubenesque/__init__.py
dslink/rubenesque/lcodec.py
dslink/rubenesque/math.py
dslink/rubenesque/codecs/__init__.py
dslink/rubenesque/codecs/cfrg.py
dslink/rubenesque/codecs/jwk.py
dslink/rubenesque/codecs/sec.py
dslink/rubenesque/curves/__init__.py
dslink/rubenesque/curves/base.py
dslink/rubenesque/curves/brainpool.py
dslink/rubenesque/curves/cfrg.py
dslink/rubenesque/curves/edwards.py
dslink/rubenesque/curves/mdc.py
dslink/rubenesque/curves/prime.py
dslink/rubenesque/curves/sec.py
dslink/rubenesque/curves/weierstrass.py
dslink/rubenesque/signatures/__init__.py
dslink/rubenesque/signatures/ecdsa.py