Metadata-Version: 1.0
Name: dslink
Version: 0.7.2
Summary: DSLink SDK for Python
Home-page: http://github.com/IOT-DSA/sdk-dslink-python
Author: Logan Gorence
Author-email: Logan.Gorence@AcuityBrands.com
License: Apache 2.0
Platform: UNKNOWN
